fenpy/__init__.py
fenpy-0.1.dist-info/LICENSE
fenpy-0.1.dist-info/METADATA
fenpy-0.1.dist-info/WHEEL
fenpy-0.1.dist-info/top_level.txt
fenpy-0.1.dist-info/RECORD
