Metadata-Version: 2.1
Name: fenpy
Version: 0.1
Summary: A computational intelligence package.
Home-page: https://github.com/davidhuangal/fenpy
Author: David Huangal
Author-email: dbhuangal1204@gmail.com
License: MIT
Platform: UNKNOWN
